run.py
ec2_session_gate-1.0.3.dist-info/licenses/LICENSE
src/__init__.py
src/api.py
src/app.py
src/aws_manager.py
src/constants.py
src/defaults.json
src/health.py
src/logging.yaml
src/preferences_handler.py
src/ui.py
src/utils.py
src/version.py
src/static/css/style.css
src/static/images/logo.icns
src/static/images/logo.ico
src/static/images/logo.png
src/static/js/app.js
src/static/templates/index.html
ec2_session_gate-1.0.3.dist-info/METADATA
ec2_session_gate-1.0.3.dist-info/WHEEL
ec2_session_gate-1.0.3.dist-info/entry_points.txt
ec2_session_gate-1.0.3.dist-info/top_level.txt
ec2_session_gate-1.0.3.dist-info/RECORD
