Metadata-Version: 2.4
Name: ec2-session-gate
Version: 1.0.3
Summary: Cross-platform AWS SSM tunnel/connection manager for EC2 instances
Home-page: https://github.com/boussaffawalid/ec2-session-gate
Author: Walid Boussafa
Author-email: Walid Boussafa <walid.boussafa@outlook.com>
License: MIT
Project-URL: Homepage, https://github.com/boussaffawalid/ec2-session-gate
Project-URL: Documentation, https://github.com/boussaffawalid/ec2-session-gate#readme
Project-URL: Repository, https://github.com/boussaffawalid/ec2-session-gate
Project-URL: Issues, https://github.com/boussaffawalid/ec2-session-gate/issues
Keywords: aws,ec2,ssm,session-manager,ssh,rdp,port-forwarding,tunnel
Classifier: Development Status :: 4 - Beta
Classifier: Intended Audience :: Developers
Classifier: Intended Audience :: System Administrators
Classifier: License :: OSI Approved :: MIT License
Classifier: Operating System :: OS Independent
Classifier: Operating System :: Microsoft :: Windows
Classifier: Operating System :: MacOS
Classifier: Operating System :: POSIX :: Linux
Classifier: Programming Language :: Python :: 3
Classifier: Programming Language :: Python :: 3.9
Classifier: Programming Language :: Python :: 3.10
Classifier: Programming Language :: Python :: 3.11
Classifier: Programming Language :: Python :: 3.12
Classifier: Topic :: System :: Networking
Classifier: Topic :: System :: Systems Administration
Classifier: Topic :: Internet :: WWW/HTTP :: Dynamic Content
Classifier: Topic :: Software Development :: Libraries :: Python Modules
Requires-Python: >=3.9
License-File: LICENSE
Requires-Dist: Flask>=2.3
Requires-Dist: boto3>=1.34
Requires-Dist: botocore>=1.34
Requires-Dist: PyYAML>=6.0
Requires-Dist: pywebview>=4.0
Requires-Dist: cryptography>=41.0
Requires-Dist: psutil>=5.9.0
Provides-Extra: dev
Requires-Dist: pytest>=7.4.0; extra == "dev"
Requires-Dist: pytest-mock>=3.11.0; extra == "dev"
Requires-Dist: pytest-cov>=4.1.0; extra == "dev"
Dynamic: author
Dynamic: home-page
Dynamic: license-file
Dynamic: requires-python
